{"cameraMode":{"drawMode":0,"name":"Shaded","section":"Shading Mode"},"sceneLighting":true,"audioPlay":false,"sceneViewState":{"showFog":true,"showMaterialUpdate":false,"showSkybox":true,"showFlares":true,"showImageEffects":true,"showParticleSystems":true},"in2DMode":false,"pivot":{"x":6.489999771118164,"y":1.4500000476837159,"z":0.46000000834465029},"rotation":{"x":-0.01803884282708168,"y":0.69770348072052,"z":0.017579082399606706,"w":0.7159443497657776},"size":4.217052936553955,"orthographic":false}